{
    "ZOMATO":{
        "CONFIG":{
            "STARTER":{
                "URL":"https://www.zomato.com/bangalore",
                "BEAUTIFUL_SOUP":true,
                "SELECTORS":{
                    "WAIT":{
                        "TAG":"a",
                        "FIND_BY":"class",
                        "VALUE":"col-l-1by3 col-s-8 pbot0"
                    }
                }
            },
            "RESTAURANT":{
                "BEAUTIFUL_SOUP": true,
                "SELECTORS":{
                    "WAIT":{
                        "TAG":"article",
                        "FIND_BY":"class",
                        "VALUE":"search-result"
                    },
                    "NAME": {
                        "TAG":"a",
                        "FIND_BY":"class",
                        "VALUE":"result-title hover_feedback zred bold ln24   fontsize0 "
                    },
                    "IMAGE":{
                        "TAG":"a",
                        "FIND_BY":"class",
                        "VALUE":"feat-img lazy",
                        "ATTRIBUTE":"data-original"
                    },
                    "URL":{
                        "TAG":"a",
                        "FIND_BY":"class",
                        "VALUE":"result-title hover_feedback zred bold ln24   fontsize0 ",
                        "ATTRIBUTE":"href"
                    },
                    "TYPE":{
                        "TAG":"span",
                        "FIND_BY":"class",
                        "VALUE":"col-s-11 col-m-12 nowrap  pl0"
                    },
                    "OPENS_AT":{
                        "TAG":"div",
                        "FIND_BY":"class",
                        "VALUE":"col-s-11 col-m-12 pl0 search-grid-right-text "
                    },
                    "STARS":{
                        "TAG":"div",
                        "FIND_BY":"class",
                        "VALUE":"ta-right floating search_result_rating col-s-4 clearfix"
                    },
                    "RATINGS":{
                        "TAG":"div",
                        "FIND_BY":"class",
                        "VALUE":"ta-right floating search_result_rating col-s-4 clearfix"
                    },
                    "NEXT_URL":{
                        "TAG":"a",
                        "FIND_BY":"class",
                        "VALUE":"next",
                        "ATTRIBUTE":"href"
                    }
                }
            },
            "DISH":{
                "BEAUTIFUL_SOUP": false,
                "SELECTORS":{
                    "WAIT":{
                        "FIND_BY":"class",
                        "VALUE":"menu-container"
                    },
                    "MENU_CONTAINER":{
                        "FIND_BY":"id",
                        "VALUE":"menu_ctg_"
                    },
                    "CONTENT":{
                        "FIND_BY":"class",
                        "VALUE":"content"
                    },
                    "NAME":{
                        "FIND_BY":"class",
                        "VALUE":"header"
                    },
                    "PRICE":{
                        "FIND_BY":"class",
                        "VALUE":"description"
                    },
                    "IMAGE":{
                        "FIND_BY":"tag",
                        "VALUE":"img",
                        "ATTRIBUTE": "src"
                    },
                    "DESCRIPTION":{
                        "FIND_BY":"class",
                        "VALUE":"meta"
                    }
                }
            }
        }
    },
    "BEHROUZ_BIRYANI":{
        "CONFIG":{
            "STARTER":{
                "URL":"https://www.behrouzbiryani.com/bangalore/residency-road",
                "BEAUTIFUL_SOUP":false,
                "SELECTORS":{
                    "WAIT":{
                        "TAG":"a",
                        "FIND_BY":"class",
                        "VALUE":"col-l-1by3 col-s-8 pbot0"
                    },
                    "IMAGE_CONTAINER":{
                        "FIND_BY":"class",
                        "VALUE":"carouselImgContainer"
                    }
                }
            },
            "DISH":{
                "BEAUTIFUL_SOUP": false,
                "SELECTORS":{
                    "WAIT":{
                        "FIND_BY":"class",
                        "VALUE":"collectionsWrapper"
                    },
                    "CATEGORY_NAV":{
                        "FIND_BY":"class",
                        "VALUE":"collectionNames"
                    },
                    "CATEGORIES":{
                        "FIND_BY":"class",
                        "VALUE":"collectionNameContainer"
                    },
                    "CONTAINER":{
                        "FIND_BY":"id",
                        "VALUE":"collectionContainer"
                    },
                    "DATA":{
                        "FIND_BY":"class",
                        "VALUE":"productContainer"
                    },
                    "CONTENT":{
                        "FIND_BY":"class",
                        "VALUE":"productContent"
                    },
                    "PRICE":{
                        "FIND_BY":"class",
                        "VALUE":"productPrice"
                    },
                    "IMAGE":{
                        "FIND_BY":"tag",
                        "VALUE":"img",
                        "ATTRIBUTE": "src"
                    },
                    "DESCRIPTION":{
                        "FIND_BY":null,
                        "VALUE":null
                    }
                }
            }
        }
    },
    "BOX8":{
        "CONFIG":{
            "STARTER":{
                "URL":"https://box8.in/menu",
                "BEAUTIFUL_SOUP":false,
                "SELECTORS":{
                    "WAIT":{
                        "TAG":"a",
                        "FIND_BY":"class",
                        "VALUE":"menu-content-wrapper"
                    },
                    "IMAGE_CONTAINER":{
                        "FIND_BY":"class",
                        "VALUE":"carouselImgContainer"
                    }
                }
            },
            "DISH":{
                "BEAUTIFUL_SOUP": false,
                "SELECTORS":{
                    "WAIT":{
                        "FIND_BY":"class",
                        "VALUE":"menu-content-wrapper"
                    },
                    "CATEGORY_NAV":{
                        "FIND_BY":"class",
                        "VALUE":"menu-sidebar-items"
                    },
                    "CATEGORIES":{
                        "FIND_BY":"tag",
                        "VALUE":"li"
                    },
                    "CONTAINER":{
                        "FIND_BY":"id",
                        "VALUE":"category-"
                    },
                    "DATA":{
                        "FIND_BY":"class",
                        "VALUE":"ui-card"
                    },
                    "NAME":{
                        "FIND_BY":"class",
                        "VALUE":"product-label"
                    },
                    "PRICE":{
                        "FIND_BY":"class",
                        "VALUE":"prices-wrapper"
                    },
                    "BOX8_USER_PRICE":{
                        "FIND_BY":"class",
                        "VALUE":"product-pass-band-price"
                    },
                    "IMAGE":{
                        "FIND_BY":"tag",
                        "VALUE":"img",
                        "ATTRIBUTE": "src"
                    },
                    "DESCRIPTION":{
                        "FIND_BY":"class",
                        "VALUE":"product-description"
                    }
                }
            }
        }
    },
    "PIZZAHUT":{
        "CONFIG":{
            "STARTER":{
                "URL":"https://online.pizzahut.co.in/products?category=deals&id=CU00216624&redirect=true",
                "BEAUTIFUL_SOUP":false,
                "SELECTORS":{
                    "WAIT":{
                        "TAG":"a",
                        "FIND_BY":"class",
                        "VALUE":"product-content"
                    },
                    "IMAGE_CONTAINER":{
                        "FIND_BY":"class",
                        "VALUE":"carouselImgContainer"
                    },
                    "ANCHOR_TAG":{
                        "VALUE":"data-href"
                    }
                }
            },
            "DISH":{
                "BEAUTIFUL_SOUP": false,
                "SELECTORS":{
                    "URL_STRING":{
                        "VALUE":"https://online.pizzahut.co.in"
                    },
                    "WAIT":{
                        "FIND_BY":"class",
                        "VALUE":"m-container"
                    },
                    "CATEGORY_NAV":{
                        "FIND_BY":"class",
                        "VALUE":"menu-container"
                    },
                    "CATEGORIES":{
                        "FIND_BY":"class",
                        "VALUE":"single-menu-item"
                    },
                    "CONTAINER":{
                        "FIND_BY":"class",
                        "VALUE":"m-container"
                    },
                    "PRODUCTS":{
                        "FIND_BY":"tag",
                        "VALUE":"ion-col"
                    },
                    "NAME":{
                        "FIND_BY":"class",
                        "VALUE":"title-value"
                    },
                    "PRICE":{
                        "FIND_BY":"class",
                        "VALUE":"title-price"
                    },
                    "SIZE":{
                        "FIND_BY":"class",
                        "VALUE":"size-crust"
                    },
                    "IMAGE":{
                        "FIND_BY":"tag",
                        "VALUE":"img",
                        "ATTRIBUTE": "src"
                    },
                    "DESCRIPTION":{
                        "FIND_BY":"class",
                        "VALUE":"description"
                    }
                }
            }
        }
    },
    "SWIGGY":{
        "CONFIG":{
            "STARTER":{
                "URL":"https://www.swiggy.com/bangalore",
                "BEAUTIFUL_SOUP":true,
                "SELECTORS":{
                    "WAIT":{
                        "TAG":"a",
                        "FIND_BY":"class",
                        "VALUE":"_15mJL"
                    }
                }
            },
            "RESTAURANT":{
                "BEAUTIFUL_SOUP": true,
                "SELECTORS":{
                    "WAIT":{
                        "TAG":"div",
                        "FIND_BY":"class",
                        "VALUE":"_3XX_A"
                    },
                    "NAME": {
                        "TAG":"div",
                        "FIND_BY":"class",
                        "VALUE":"OEfxz"
                    },
                    "IMAGE":{
                        "TAG":"a",
                        "FIND_BY":"class",
                        "VALUE":"feat-img lazy",
                        "ATTRIBUTE":"data-original"
                    },
                    "URL":{
                        "TAG":"a",
                        "FIND_BY":"class",
                        "VALUE":"_1j_Yo",
                        "ATTRIBUTE":"href"
                    },
                    "TYPE":{
                        "TAG":"div",
                        "FIND_BY":"class",
                        "VALUE":"_3Plw0 JMACF"
                    },
                    "OPENS_AT":{
                        "TAG":"span",
                        "FIND_BY":"class",
                        "VALUE":"_1xxne _3sG9I _3m8av"
                    },
                    "STARS":{
                        "TAG":"div",
                        "FIND_BY":"class",
                        "VALUE":"_2l3H5"
                    },
                    "RATINGS":{
                        "TAG":"div",
                        "FIND_BY":"class",
                        "VALUE":"_1De48"
                    },
                    "NEXT_URL":{
                        "TAG":"a",
                        "FIND_BY":"class",
                        "VALUE":"_1FZ7A",
                        "ATTRIBUTE":"href"
                    }
                }
            },
            "DISH":{
                "BEAUTIFUL_SOUP": false,
                "SELECTORS":{
                    "WAIT":{
                        "FIND_BY":"class",
                        "VALUE":"menu-container"
                    },
                    "CONTAINER":{
                        "TAG":"div",
                        "FIND_BY":"id"
                        
                    },
                    "DATA":{
                        "TAG":"div",
                        "FIND_BY":"class",
                        "VALUE":"_2wg_t"
                    },
                    "NAME":{
                        "TAG":"div",
                        "FIND_BY":"class",
                        "VALUE":"jTy8b"
                    },
                    "PRICE":{
                        "TAG":"span",
                        "FIND_BY":"class",
                        "VALUE":"bQEAj"
                    },
                    "IMAGE":{
                        "FIND_BY":"tag",
                        "VALUE":"img",
                        "ATTRIBUTE": "src"
                    },
                    "DESCRIPTION":{
                        "TAG":"div",
                        "FIND_BY":"class",
                        "VALUE":"_2aOqz"
                    },
                    "CATEGORIES":{
                        "TAG":"a",
                        "FIND_BY":"class",
                        "VALUE":"_1gHSS"
                    },
                    "CATEGORY_TAB":{
                        "TAG":"div",
                        "FIND_BY":"class",
                        "VALUE":"_2K_ax"
                    }
                }
            }
        }
    }
}
